[
  {
    "content": "",
    "description": "",
    "tags": null,
    "title": "Categories",
    "uri": "/Personal-Wiki/categories/index.html"
  },
  {
    "content": "",
    "description": "",
    "tags": null,
    "title": "python",
    "uri": "/Personal-Wiki/tags/python/index.html"
  },
  {
    "content": "",
    "description": "",
    "tags": null,
    "title": "Search",
    "uri": "/Personal-Wiki/search/index.html"
  },
  {
    "content": "",
    "description": "",
    "tags": null,
    "title": "Tags",
    "uri": "/Personal-Wiki/tags/index.html"
  }
]
